<?xml version="1.0" encoding="UTF-8"?>
<papyrus id="orig_bin_01">
	<box char="epsilon" id="orig_bin_01_0">
		<x1>1217</x1>
		<y1>148</y1>
		<x2>1253</x2>
		<y2>213</y2>
	</box>
	<box char="epsilon" id="orig_bin_01_1">
		<x1>1662</x1>
		<y1>552</y1>
		<x2>1698</x2>
		<y2>613</y2>
	</box>
	<box char="epsilon" id="orig_bin_01_2">
		<x1>982</x1>
		<y1>944</y1>
		<x2>1026</x2>
		<y2>1003</y2>
	</box>
	<box char="epsilon" id="orig_bin_01_3">
		<x1>1515</x1>
		<y1>1129</y1>
		<x2>1558</x2>
		<y2>1193</y2>
	</box>
	<box char="epsilon" id="orig_bin_01_4">
		<x1>386</x1>
		<y1>1244</y1>
		<x2>427</x2>
		<y2>1306</y2>
	</box>
	<box char="epsilon" id="orig_bin_01_5">
		<x1>1097</x1>
		<y1>1331</y1>
		<x2>1136</x2>
		<y2>1391</y2>
	</box>
	<box char="epsilon" id="orig_bin_01_6">
		<x1>1498</x1>
		<y1>1335</y1>
		<x2>1539</x2>
		<y2>1395</y2>
	</box>
	<box char="epsilon" id="orig_bin_01_7">
		<x1>1314</x1>
		<y1>1427</y1>
		<x2>1350</x2>
		<y2>1481</y2>
	</box>
	<box char="epsilon" id="orig_bin_01_8">
		<x1>1129</x1>
		<y1>1526</y1>
		<x2>1170</x2>
		<y2>1584</y2>
	</box>
	<box char="epsilon" id="orig_bin_01_9">
		<x1>1101</x1>
		<y1>1626</y1>
		<x2>1139</x2>
		<y2>1688</y2>
	</box>
	<box char="epsilon" id="orig_bin_01_10">
		<x1>755</x1>
		<y1>1731</y1>
		<x2>793</x2>
		<y2>1789</y2>
	</box>
	<box char="epsilon" id="orig_bin_01_11">
		<x1>1395</x1>
		<y1>1905</y1>
		<x2>1430</x2>
		<y2>1973</y2>
	</box>
	<box char="epsilon" id="orig_bin_01_12">
		<x1>854</x1>
		<y1>2128</y1>
		<x2>890</x2>
		<y2>2190</y2>
	</box>
	<box char="epsilon" id="orig_bin_01_13">
		<x1>1149</x1>
		<y1>2128</y1>
		<x2>1188</x2>
		<y2>2188</y2>
	</box>
	<box char="epsilon" id="orig_bin_01_14">
		<x1>1857</x1>
		<y1>2219</y1>
		<x2>1896</x2>
		<y2>2281</y2>
	</box>
	<box char="epsilon" id="orig_bin_01_15">
		<x1>1704</x1>
		<y1>2494</y1>
		<x2>1733</x2>
		<y2>2562</y2>
	</box>
</papyrus>
